{"customers":[    
    {"name":"Emily Kane", "email":"Emily.Kane@ding.com", "balance":19},    
    {"name":"Hugh O'Donoghue", "email":"Hugh.ODonoghue@ding.com", "balance":8},  
    {"name":"Megan Coleman", "email":"Megan.Coleman@ding.com", "balance":5},    
    {"name":"Padraig O'Donnell", "email":"Padraig.ODonnell@ding.com", "balance":11},
	{"name":"Roisin Doherty", "email":"Roisin.Doherty@ding.com", "balance":3},    
    {"name":"Hugh O'Donoghue", "email":"Hugh.ODonoghue@ding.com", "balance":15},  
    {"name":"James Hall", "email":"James.Hall@ding.com", "balance":13},    
    {"name":"Johary Rabesetra", "email":"Johary.Rabesetra@ding.com", "balance":1},
	{"name":"Tushar Patil", "email":"Tushar.Patil@ding.com", "balance":0},    
    {"name":"Mayla Gonzalez", "email":"Mayla.Gonzalez@ding.com", "balance":17},
]}